LICENSE
MANIFEST.in
README.md
pyproject.toml
requirements-dev.txt
requirements.txt
setup.py
ibm_project_sdk/__init__.py
ibm_project_sdk/common.py
ibm_project_sdk/project_v1.py
ibm_project_sdk/version.py
ibm_project_sdk.egg-info/PKG-INFO
ibm_project_sdk.egg-info/SOURCES.txt
ibm_project_sdk.egg-info/dependency_links.txt
ibm_project_sdk.egg-info/requires.txt
ibm_project_sdk.egg-info/top_level.txt
ibm_project_sdk.egg-info/zip-safe