Metadata-Version: 2.1
Name: ibm-project-sdk
Version: 0.0.3
Summary: Project Services Python SDK
Home-page: https://github.com/IBM/project-python-sdk
Author: IBM
Author-email: dvesperini@gmail.com
License: Apache 2.0
Keywords: ibm_project_sdk
Platform: UNKNOWN
Classifier: Programming Language :: Python
Classifier: Programming Language :: Python :: 3
Classifier: Programming Language :: Python :: 3.7
Classifier: Programming Language :: Python :: 3.8
Classifier: Programming Language :: Python :: 3.9
Classifier: Programming Language :: Python :: 3.10
Classifier: Development Status :: 4 - Beta
Classifier: Intended Audience :: Developers
Classifier: License :: OSI Approved :: Apache Software License
Classifier: Operating System :: OS Independent
Classifier: Topic :: Software Development :: Libraries :: Python Modules
Classifier: Topic :: Software Development :: Libraries :: Application Frameworks
License-File: LICENSE
